Metadata-Version: 2.1
Name: confselector
Version: 1.0.1
Summary: config selector
Home-page: https://github.com/wzwjustdoit/confselector
Author: wzwjustdoit
Author-email: wzwjustdoit@163.com
Maintainer: wzwjustdoit
Maintainer-email: wzwjustdoit@163.com
License: MIT
Keywords: confselector,conf,config,selector
Platform: all
Classifier: License :: OSI Approved :: MIT License
Classifier: Programming Language :: Python
Classifier: Programming Language :: Python :: 3
Classifier: Programming Language :: Python :: 3.6
Classifier: Programming Language :: Python :: Implementation :: CPython
Classifier: Programming Language :: Python :: Implementation :: PyPy
Requires-Python: >=3.0.0
